{ "_id" : { "$oid" : "515af134f4158eed2e4d1c0c" }, "fecha_alta" : "02/12/2011", "activo" : 1, "escano_actual" : 2709, "id" : 234, "apellidos" : "Villanova Rueda", "nombre" : "Joaquín", "sexo" : "H", "circunscripcion" : "Málaga", "partido" : "PP", "grupo" : "Popular", "fecha_nac" : "11/01/1957", "lugar_nac" : "Málaga", "actividad" : [ { "fecha" : "15-04-2013", "intervenciones" : { "pleno" : 2, "comision" : 7, "dipuPerm" : 0, "otras" : 0, "total" : 9 }, "iniciativas" : { "preg_orales" : 0, "preg_escritas" : 42, "solicit_comparecencias" : 0, "solicit_informes" : 0, "solicit_nuevo_organo" : 0, "total" : 42 } } ], "relaciones" : "Casado. Dos hijos", "tuvo_cargos_publicos" : 1, "estuvo_empresas_priv" : 1, "estudios" : [ { "estudio" : "Título en Técnico de Administración de Empresas" } ], "trayectoria" : [ { "cargo" : "Jefe de contabilidad de la empresa Punto Industrial, S.A.", "fini" : "1980", "ffin" : "1980" }, { "cargo" : "Jefe de Administración de la empresa Promociones Arroyo del Pinar", "fini" : "1982", "ffin" : "1996" }, { "cargo" : "Concejal del Ayuntamiento de Alhaurín de la Torre", "fini" : "1987", "ffin" : "1995" }, { "cargo" : "Alcalde del Ayuntamiento de Alhaurín de la Torre", "fini" : "1996", "ffin" : "2003" }, { "cargo" : "Senador por Málaga e la VII Legislatura", "fini" : "2000", "ffin" : "2004" } ], "cargos_congreso" : [ { "tipoOrgano" : "C", "idOrgano" : 306, "cargo" : "V", "alta" : "18/01/2012", "baja" : "23/07/2012" }, { "tipoOrgano" : "C", "idOrgano" : 311, "cargo" : "V", "alta" : "24/10/2012" }, { "tipoOrgano" : "C", "idOrgano" : 311, "cargo" : "A", "alta" : "04/06/2012", "baja" : "24/10/2012" }, { "tipoOrgano" : "C", "idOrgano" : 307, "cargo" : "V", "alta" : "17/01/2012" }, { "tipoOrgano" : "C", "idOrgano" : 317, "cargo" : "V", "alta" : "08/02/2012" }, { "tipoOrgano" : "C", "idOrgano" : 322, "cargo" : "POA", "alta" : "08/02/2012" } ], "sueldo" : { "desglose" : [ { "cantidad" : 2813.87, "concepto" : "Asignación constitucional para todos los diputados", "tributa" : 1 }, { "cantidad" : 1823.86, "concepto" : "Indemnización para los diputados no electos por Madrid", "tributa" : 0 }, { "cantidad" : 697.65, "concepto" : "Portavoz Adjunto de Comisión", "tributa" : 1 } ], "bruto_mes" : 5335.38 } }
