{ "_id" : { "$oid" : "515af426f4158eed2e4d1c2c" }, "fecha_alta" : "05/12/2011", "activo" : 1, "escano_actual" : 1206, "id" : 266, "apellidos" : "Carcedo Roces", "nombre" : "María Luisa", "sexo" : "M", "circunscripcion" : "Asturias", "partido" : "PSOE", "grupo" : "Socialista", "fecha_nac" : "30/08/1953", "lugar_nac" : "San Martín del Rey Aurelio (Asturias)", "legislaturas" : [ "VIII", "IX" ], "contacto" : [ { "tipo" : "wikipedia", "url" : "http://es.wikipedia.org/wiki/Mar%C3%ADa_Luisa_Carcedo", "oficial" : 0 } ], "actividad" : [ { "fecha" : "15-04-2013", "intervenciones" : { "pleno" : 7, "comision" : 3, "dipuPerm" : 14, "otras" : 0, "total" : 24 }, "iniciativas" : { "preg_orales" : 2, "preg_escritas" : 47, "solicit_comparecencias" : 0, "solicit_informes" : 1, "solicit_nuevo_organo" : 0, "total" : 50 } } ], "relaciones" : "Casada. Un hijo", "tuvo_cargos_publicos" : 1, "estuvo_empresas_priv" : 0, "estudios" : [ { "centro" : "Universidad de Oviedo", "estudio" : "Licenciatura en Medicina y Cirugía" }, { "estudio" : "Diplomatura en Medicina del Trabajo" } ], "trayectoria" : [ { "cargo" : "Médica en Atención Primaria de Salud en Servicio de Salud de Asturias (SESPA)", "fini" : "1978", "ffin" : "1984" }, { "cargo" : "Directora Sectorial de Ambulatorios en el Área Sanitaria del Valle del Nalón", "fini" : "1984", "ffin" : "1988" }, { "cargo" : "Directora Regional de Salud Pública del Principado de Asturias" }, { "cargo" : "Diputada en la Junta General del Principado de Asturias", "fini" : "1991", "ffin" : "2004" }, { "cargo" : "Consejera de Medio Ambiente y Urbanismo del Principado de Asturias", "fini" : "1991", "ffin" : "1995" }, { "cargo" : "Presidenta de la Agencia Estatal de Evaluación Politicas Públicas y Calidad Servicios (AEVAL)", "fini" : "2008", "ffin" : "2008" } ], "cargos_congreso" : [ { "tipoOrgano" : "JP", "cargo" : "POS", "alta" : "14/02/2012" }, { "tipoOrgano" : "DP", "cargo" : "V", "alta" : "29/06/2012" }, { "tipoOrgano" : "C", "idOrgano" : 311, "cargo" : "V", "alta" : "17/01/2012", "baja" : "21/02/2012" }, { "tipoOrgano" : "C", "idOrgano" : 311, "cargo" : "A", "alta" : "21/02/2012" }, { "tipoOrgano" : "C", "idOrgano" : 305, "cargo" : "A", "alta" : "06/03/2012" }, { "tipoOrgano" : "C", "idOrgano" : 310, "cargo" : "A", "alta" : "06/03/2012" }, { "tipoOrgano" : "C", "idOrgano" : 308, "cargo" : "PO", "alta" : "17/01/2012", "baja" : "06/03/2012" }, { "tipoOrgano" : "C", "idOrgano" : 308, "cargo" : "V", "alta" : "06/03/2012" }, { "tipoOrgano" : "C", "idOrgano" : 325, "cargo" : "V", "alta" : "18/01/2012", "baja" : "18/10/2012" }, { "tipoOrgano" : "C", "idOrgano" : 325, "cargo" : "A", "alta" : "18/10/2012" }, { "tipoOrgano" : "C", "idOrgano" : 330, "cargo" : "A", "alta" : "06/03/2012" }, { "tipoOrgano" : "C", "idOrgano" : 320, "cargo" : "A", "alta" : "06/03/2012" }, { "tipoOrgano" : "C", "idOrgano" : 312, "cargo" : "V", "alta" : "21/02/2012" }, { "tipoOrgano" : "C", "idOrgano" : 343, "cargo" : "A", "alta" : "06/03/2012" }, { "tipoOrgano" : "C", "idOrgano" : 345, "cargo" : "A", "alta" : "06/03/2012" }, { "tipoOrgano" : "C", "idOrgano" : 322, "cargo" : "A", "alta" : "06/03/2012" } ], "sueldo" : { "desglose" : [ { "cantidad" : 2813.87, "concepto" : "Asignación constitucional para todos los diputados", "tributa" : 1 }, { "cantidad" : 1823.86, "concepto" : "Indemnización para los diputados no electos por Madrid", "tributa" : 0 }, { "cantidad" : 2087.07, "concepto" : "Portavoz Sustituta del Grupo Parlamentario Socialista", "tributa" : 1 } ], "bruto_mes" : 6724.8 } }
