{ "_id" : { "$oid" : "515b0038f4158eed2e4d1c98" }, "fecha_alta" : "08/10/2012", "activo" : 1, "id_sustituido" : 351, "escano_actual" : 5802, "id" : 374, "apellidos" : "Rodríguez Flores", "nombre" : "María Carmen", "sexo" : "M", "circunscripcion" : "Madrid", "partido" : "PP", "grupo" : "Popular", "fecha_nac" : "28/06/1943", "lugar_nac" : "Madrid", "contacto" : [ { "tipo" : "web", "url" : "http://www.asambleamadrid.es/AsambleaDeMadrid/ES/QueEsLaAsamblea/ComposicionAsamblea/CVs/Maria+Carmen+Rodriguez+Flores.htm", "oficial" : 0 } ], "actividad" : [ { "fecha" : "15-04-2013", "intervenciones" : { "pleno" : 0, "comision" : 0, "dipuPerm" : 0, "otras" : 0, "total" : 0 }, "iniciativas" : { "preg_orales" : 0, "preg_escritas" : 0, "solicit_comparecencias" : 0, "solicit_informes" : 0, "solicit_nuevo_organo" : 0, "total" : 0 } } ], "relaciones" : "Un hijo. Tres nietos", "tuvo_cargos_publicos" : 1, "estuvo_empresas_priv" : 1, "estudios" : [ { "centro" : "Universidad Complutense de Madrid", "estudio" : "Licenciatura en Ciencias Químicas" }, { "centro" : "Consejo Superior de Investigaciones Científicas de Madrid", "estudio" : "Curso de alta especialización sobre Materiales Plásticos" }, { "centro" : "piano, canto", "estudio" : "Estudios musicales" } ], "trayectoria" : [ { "cargo" : "Concejal de Sanidad del Ayuntamiento de Villaviciosa de Odón (Madrid)" }, { "cargo" : "Concejal del Ayuntamiento de Madrid durante dos legislaturas. Distrito Hortaleza y Distrito Barajas" }, { "cargo" : "Diputada Autonómica de la Asamblea de Madrid durante dos legislaturas." }, { "cargo" : "Concejal del Ayuntamiento de Madrid (Concejalía Arganzuela)" }, { "cargo" : "Propaganda y organización de campañas electorales de Alianza Popular y Partido Popular" }, { "cargo" : "Oficina de Empleo del Partido Popular" }, { "cargo" : "Miembro del Comité Ejecutivo Regional de Madrid y Junta Directiva Regional" }, { "cargo" : "Consejera de Caja Madrid" }, { "cargo" : "Consejera de Madrid 2012" }, { "cargo" : "Diputada de la X legislatura", "fini" : "2011", "ffin" : 0 } ], "cargos_congreso" : [ { "tipoOrgano" : "C", "idOrgano" : 329, "cargo" : "V", "alta" : "24/10/2012" }, { "tipoOrgano" : "C", "idOrgano" : 325, "cargo" : "A", "alta" : "24/10/2012" }, { "tipoOrgano" : "C", "idOrgano" : 326, "cargo" : "V", "alta" : "24/10/2012" }, { "tipoOrgano" : "C", "idOrgano" : 330, "cargo" : "V", "alta" : "24/10/2012" } ], "sueldo" : { "desglose" : [ { "cantidad" : 2813.87, "concepto" : "Asignación constitucional para todos los diputados", "tributa" : 1 }, { "cantidad" : 870.5599999999999, "concepto" : "Indemnización para los diputados electos por Madrid", "tributa" : 0 } ], "bruto_mes" : 3684.43 } }
